guesspkgabc/__init__.py
guesspkgabc/guess.py
guesspkgabc-0.0.4.1.dist-info/METADATA
guesspkgabc-0.0.4.1.dist-info/WHEEL
guesspkgabc-0.0.4.1.dist-info/top_level.txt
guesspkgabc-0.0.4.1.dist-info/RECORD
